{
  "account_reference_list": [
    {
      "kind": "account",
      "uuid": "955f5022-96ce-4f2c-8538-a65f9d151c61"
    }
  ],
  "resource_domain": {
    "resources": [
      {
        "units": "COUNT",
        "value": 0,
        "resource_type": "VMS"
      },
      {
        "units": "BYTES",
        "value": 0,
        "resource_type": "STORAGE"
      },
      {
        "units": "COUNT",
        "value": 0,
        "resource_type": "VCPUS"
      },
      {
        "units": "BYTES",
        "value": 0,
        "resource_type": "MEMORY"
      }
    ]
  },
  "environment_reference_list": [
    {
      "kind": "environment",
      "uuid": "f828caf8-e962-f230-9e73-fd47744fac33"
    }
  ],
  "default_subnet_reference": {
    "kind": "subnet",
    "uuid": "15de6a35-4daa-405c-bd71-5cad7ebf350b"
  },
  "user_reference_list": [
    {
      "kind": "user",
      "name": "alaindev@emeagso.lab",
      "uuid": "3b559f21-00a0-5c87-9ade-e10bbf37e5e6"
    }
  ],
  "tunnel_reference_list": [],
  "external_user_group_reference_list": [],
  "cluster_reference_list": [
    {
      "kind": "cluster",
      "uuid": "000582c6-cf0d-e0a8-0000-000000016950"
    }
  ],
  "subnet_reference_list": [
    {
      "kind": "subnet",
      "name": "VLAN202",
      "uuid": "3b915221-76a9-4216-aa20-20da38e4a31e"
    },
    {
      "kind": "subnet",
      "name": "VLAN201",
      "uuid": "15de6a35-4daa-405c-bd71-5cad7ebf350b"
    }
  ],
  "vpc_reference_list": [],
  "external_network_list": [],
  "default_environment_reference": {
    "kind": "environment",
    "uuid": "f828caf8-e962-f230-9e73-fd47744fac33"
  }
}
